gam_g4/gam_g4.cpython-35m-x86_64-linux-gnu.so
gam_g4/__init__.py
gam_g4/gam_lib/__init__.py
gam_g4/g4_bindings/__init__.py
tryGam.libs/libfftw3-17cc48a2.so.3.3.2
tryGam.libs/libexpat-3e0b9453.so.1.6.0
tryGam.libs/libG4visHepRep-be94b8d5.so
tryGam.libs/libG4physicslists-628745c9.so
tryGam.libs/libG4geometry-0231e797.so
tryGam.libs/libG4error_propagation-269d3d6e.so
tryGam.libs/libG4global-f150304d.so
tryGam.libs/libG4intercoms-5923bb97.so
tryGam.libs/libG4processes-a65d48eb.so
tryGam.libs/libG4vis_management-7c398554.so
tryGam.libs/libG4particles-e28b1f8b.so
tryGam.libs/libG4clhep-67a3fff6.so
tryGam.libs/libG4interfaces-43917445.so
tryGam.libs/libG4Tree-dc5ab08c.so
tryGam.libs/libG4graphics_reps-c1a0dda7.so
tryGam.libs/libG4VRML-993e201c.so
tryGam.libs/libG4persistency-9dbfb712.so
tryGam.libs/libG4parmodels-d84b5f33.so
tryGam.libs/libG4analysis-65caf465.so
tryGam.libs/libfftw3f_threads-de15b4b8.so.3.3.2
tryGam.libs/libfftw3_threads-1d56c0c3.so.3.3.2
tryGam.libs/libG4digits_hits-bf5888c5.so
tryGam.libs/libG4modeling-d0232305.so
tryGam.libs/libG4tracking-dbeb3753.so
tryGam.libs/libG4FR-713ccf72.so
tryGam.libs/libG4zlib-0e394b0b.so
tryGam.libs/libG4RayTracer-65635ec5.so
tryGam.libs/libG4GMocren-5916dd67.so
tryGam.libs/libG4run-455dca42.so
tryGam.libs/libG4readout-494b4ec4.so
tryGam.libs/libfftw3f-4367ce36.so.3.3.2
tryGam.libs/libG4track-59291f24.so
tryGam.libs/libG4materials-f2ce6399.so
tryGam.libs/libG4event-fddc6c02.so
tryGam-0.0.3.dist-info/WHEEL
tryGam-0.0.3.dist-info/top_level.txt
tryGam-0.0.3.dist-info/RECORD
tryGam-0.0.3.dist-info/METADATA
tryGam-0.0.3.dist-info/LICENCE.md
