Metadata-Version: 2.1
Name: tryGam
Version: 0.0.3
Summary: A test project using pybind11 and CMake
Home-page: UNKNOWN
Author: Opengate Collaboration
Author-email: thomas.baudier@creatis.insa-lyon.fr
License: UNKNOWN
Platform: UNKNOWN
